{"navItems":{"name":"","children":[{"code":"summary","name":"Summary","children":[],"href":"/summary","order":-1},{"code":"letter-to-thor","name":"Letter to Thor","children":[],"href":"/letter-to-thor","order":0},{"code":"preface","name":"Preface","children":[],"href":"/preface","order":2},{"code":"background","name":"Background","children":[{"code":"who-is-lyric","name":"Who is Lyric?","children":[],"href":"/background/who-is-lyric","order":1},{"code":"who-is-thor","name":"Who is Thor?","children":[],"href":"/background/who-is-thor","order":3}],"href":"","order":3},{"code":"conversations","name":"Conversations","children":[{"code":"love-bombing","name":"Love Bombing","children":[],"href":"/conversations/love-bombing","order":0},{"code":"moving","name":"Moving","children":[],"href":"/conversations/moving","order":0},{"code":"cheating","name":"Cheating","children":[],"href":"/conversations/cheating","order":2},{"code":"no-means-yes","name":"\"No\" Means Yes","children":[],"href":"/conversations/no-means-yes","order":3},{"code":"thors-goals","name":"Thor's Goals","children":[],"href":"/conversations/thors-goals","order":3},{"code":"abandonment","name":"Abandonment","children":[],"href":"/conversations/abandonment","order":6},{"code":"dating-thor","name":"\"Dating\" Thor","children":[],"href":"/conversations/dating-thor","order":10}],"href":"","order":4},{"code":"donations","name":"Donations","children":[{"code":"donate-your-savings","name":"Donate Your Savings","children":[],"href":"/donations/donate-your-savings","order":0},{"code":"kickstarter","name":"Kickstarter","children":[],"href":"/donations/kickstarter","order":1}],"href":"","order":5},{"code":"twitchcon-2018","name":"TwitchCon 2018","children":[{"code":"meetup","name":"Meetup","children":[],"href":"/twitchcon-2018/meetup","order":0},{"code":"final-conversation","name":"Final Conversation","children":[],"href":"/twitchcon-2018/final-conversation","order":99}],"href":"","order":6},{"code":"aftermath","name":"Aftermath","children":[{"code":"timeline","name":"Timeline","children":[],"href":"/aftermath/timeline","order":-1},{"code":"lyrics-chargeback","name":"Lyric's Chargeback","children":[],"href":"/aftermath/lyrics-chargeback","order":1},{"code":"thors-publicization","name":"Thor's Publicisation","children":[],"href":"/aftermath/thors-publicization","order":2},{"code":"thors-copyright-strike","name":"Thor's Copyright Strike","children":[],"href":"/aftermath/thors-copyright-strike","order":3},{"code":"lyrics-twitter-post","name":"Lyric's Twitter Post","children":[],"href":"/aftermath/lyrics-twitter-post","order":4},{"code":"lyrics-google-doc","name":"Lyric's Google Doc","children":[],"href":"/aftermath/lyrics-google-doc","order":6},{"code":"thors-proxy-blackmail","name":"Thor's Proxy Blackmail","children":[],"href":"/aftermath/thors-proxy-blackmail","order":7},{"code":"thors-defense","name":"Thor's Defense","children":[],"href":"/aftermath/thors-defense","order":8},{"code":"effects-on-my-life","name":"Effects on my Life","children":[],"href":"/aftermath/effects-on-my-life","order":10}],"href":"","order":7},{"code":"sources","name":"Sources","children":[{"code":"misc","name":"Misc. Sources","children":[],"href":"/sources/misc","order":0},{"code":"recent-events","name":"Recent Events","children":[],"href":"/sources/recent-events","order":0},{"code":"telegram-archive","name":"Telegram Archive","children":[],"href":"/sources/telegram-archive","order":0},{"code":"thors-marriage","name":"Thor's Marriage","children":[],"href":"/sources/thors-marriage","order":0},{"code":"thors-discord","name":"Thor's Discord","children":[],"href":"/sources/thors-discord","order":5},{"code":"recollection-of-twitchcon","name":"Recollection of TwitchCon","children":[],"href":"/sources/recollection-of-twitchcon","order":7},{"code":"discord-dms","name":"Discord DMs","children":[],"href":"/sources/discord-dms","order":99},{"code":"twitter-thread","name":"Twitter Thread","children":[],"href":"/sources/twitter-thread","order":99}],"href":"","order":8},{"code":"asides","name":"Asides","children":[{"code":"darvo","name":"DARVO","children":[],"href":"/asides/darvo","order":3},{"code":"community-feedback","name":"Community Feedback","children":[],"href":"/asides/community-feedback","order":99},{"code":"motivation","name":"Motivation","children":[],"href":"/asides/motivation","order":99},{"code":"shame","name":"Shame","children":[],"href":"/asides/shame","order":99}],"href":"","order":9}],"href":""},"mdMetadata":{"/aftermath/effects-on-my-life":{"title":"Effects on my Life","order":10,"headings":[{"level":2,"title":"Career","slug":"career"},{"level":2,"title":"YouTube","slug":"youtube"}]},"/aftermath/lyrics-chargeback":{"title":"Lyric's Chargeback","order":1,"headings":[{"level":2,"title":"Feb 2 to March 22, 2019","slug":"feb-2-to-march-22-2019"},{"level":2,"title":"Reflection","slug":"reflection"},{"level":2,"title":"Feedback","slug":"feedback"},{"level":2,"title":"Public References","slug":"public-references"},{"level":2,"title":"Timeline of Transactions","slug":"timeline-of-transactions"}]},"/aftermath/lyrics-google-doc":{"title":"Lyric's Google Doc","order":6,"headings":[{"level":2,"title":"Analyzing the Doc","slug":"analyzing-the-doc"},{"level":2,"title":"Feedback","slug":"feedback"},{"level":2,"title":"Addressing Feedback","slug":"addressing-feedback"},{"level":2,"title":"All feedback received","slug":"all-feedback-received"}]},"/aftermath/lyrics-twitter-post":{"title":"Lyric's Twitter Post","order":4,"headings":[]},"/aftermath/thors-copyright-strike":{"title":"Thor's Copyright Strike","order":3,"headings":[{"level":2,"title":"Thor’s Public Portrayal","slug":"thors-public-portrayal"},{"level":2,"title":"Videos Not Monetized","slug":"videos-not-monetized"},{"level":2,"title":"Thor’s Free Publicity","slug":"thors-free-publicity"}]},"/aftermath/thors-defense":{"title":"Thor's Defense","order":8,"important":true,"headings":[{"level":2,"title":"“Thor is divorced.”","slug":"thor-is-divorced"},{"level":2,"title":"“Lyric doxxed Thor / Altered messages.”","slug":"lyric-doxxed-thor--altered-messages"},{"level":2,"title":"“Lyric planned this and he is a scammer.”","slug":"lyric-planned-this-and-he-is-a-scammer"}]},"/aftermath/thors-proxy-blackmail":{"title":"Thor's Proxy Blackmail","order":7,"important":true,"headings":[{"level":2,"title":"Shaye lies to my partner","slug":"shaye-lies-to-my-partner"},{"level":2,"title":"My partner tries to convince me","slug":"my-partner-tries-to-convince-me"},{"level":2,"title":"Deleting my posts","slug":"deleting-my-posts"},{"level":2,"title":"Transcripts","slug":"transcripts"}]},"/aftermath/thors-publicization":{"title":"Thor's Publicisation","order":2,"headings":[]},"/aftermath/timeline":{"title":"Timeline","wip":true,"order":-1,"headings":[]},"/asides/community-feedback":{"title":"Community Feedback","order":99,"headings":[]},"/asides/darvo":{"title":"DARVO","order":3,"headings":[{"level":2,"title":"DARVO","slug":"darvo"},{"level":2,"title":"Attack vs Reverse Victim and Offender","slug":"attack-vs-reverse-victim-and-offender"}]},"/asides/motivation":{"title":"Motivation","order":99,"headings":[{"level":2,"title":"Motivation","slug":"motivation"},{"level":3,"title":"Past","slug":"past"},{"level":3,"title":"Interim","slug":"interim"},{"level":3,"title":"Present - Retrospect","slug":"present---retrospect"}]},"/asides/shame":{"title":"Shame","order":99,"headings":[]},"/background/who-is-lyric":{"title":"Who is Lyric?","order":1,"headings":[]},"/background/who-is-thor":{"title":"Who is Thor?","order":3,"headings":[{"level":2,"title":"Thor’s Online Presence","slug":"thors-online-presence"},{"level":2,"title":"Shaye’s Online Presence","slug":"shayes-online-presence"}]},"/conversations/abandonment":{"title":"Abandonment","order":6,"headings":[{"level":2,"title":"Annotated Transcript","slug":"annotated-transcript"}]},"/conversations/cheating":{"title":"Cheating","order":2,"headings":[{"level":2,"title":"Pulling Back","slug":"pulling-back"},{"level":2,"title":"Roleplaying","slug":"roleplaying"},{"level":2,"title":"Shaming","slug":"shaming"},{"level":2,"title":"Transcript","slug":"transcript"}]},"/conversations/dating-thor":{"title":"\"Dating\" Thor","order":10,"headings":[{"level":3,"title":"Annotated Transcript","slug":"annotated-transcript"}]},"/conversations/love-bombing":{"title":"Love Bombing","order":0,"headings":[{"level":2,"title":"Dedication","slug":"dedication"},{"level":2,"title":"Unconditional Support","slug":"unconditional-support"},{"level":2,"title":"Pet names","slug":"pet-names"},{"level":2,"title":"Training Submission","slug":"training-submission"},{"level":2,"title":"Meeting Up","slug":"meeting-up"}]},"/conversations/moving":{"title":"Moving","headings":[]},"/conversations/no-means-yes":{"title":"\"No\" Means Yes","order":3,"important":true,"headings":[{"level":2,"title":"1. It seemed like a healthy discussion","slug":"1-it-seemed-like-a-healthy-discussion"},{"level":2,"title":"2. Thor doesn’t accept Lyric’s boundaries","slug":"2-thor-doesnt-accept-lyrics-boundaries"},{"level":2,"title":"3. Thor says “close friends” aren’t real","slug":"3-thor-says-close-friends-arent-real"},{"level":2,"title":"4. Thor says you are already committed","slug":"4-thor-says-you-are-already-committed"},{"level":2,"title":"5. Thor defines commitment for Lyric","slug":"5-thor-defines-commitment-for-lyric"},{"level":2,"title":"Annotated Transcription","slug":"annotated-transcription"}]},"/conversations/thors-goals":{"title":"Thor's Goals","order":3,"important":true,"headings":[{"level":2,"title":"Thor Wants Money","slug":"thor-wants-money"},{"level":2,"title":"Thor Wants Obsession","slug":"thor-wants-obsession"},{"level":2,"title":"Annotated Transcript","slug":"annotated-transcript"}]},"/donations/donate-your-savings":{"title":"Donate Your Savings","headings":[{"level":2,"title":"Donate your savings","slug":"donate-your-savings"},{"level":2,"title":"Transcript","slug":"transcript"}]},"/donations/kickstarter":{"title":"Kickstarter","order":1,"important":true,"headings":[{"level":2,"title":"Thor mentions the Baron plush","slug":"thor-mentions-the-baron-plush"},{"level":2,"title":"Thor mentions the Kickstarter","slug":"thor-mentions-the-kickstarter"},{"level":2,"title":"Lyric pledges $100","slug":"lyric-pledges-100"},{"level":2,"title":"Thor mentions the Kickstarter might fail","slug":"thor-mentions-the-kickstarter-might-fail"},{"level":2,"title":"Lyric increases their pledge to $500","slug":"lyric-increases-their-pledge-to-500"},{"level":2,"title":"Thor subtly pressures Lyric to donate more","slug":"thor-subtly-pressures-lyric-to-donate-more"},{"level":2,"title":"Lyric increases their pledge to $3000","slug":"lyric-increases-their-pledge-to-3000"},{"level":2,"title":"Lyric decreases their pledge to $2000","slug":"lyric-decreases-their-pledge-to-2000"},{"level":2,"title":"Lyric decreases their pledge to $1500","slug":"lyric-decreases-their-pledge-to-1500"},{"level":2,"title":"Aftermath: Thor refunds Lyric’s pledge","slug":"aftermath-thor-refunds-lyrics-pledge"}]},"/letter-to-thor":{"title":"Letter to Thor","headings":[]},"/preface":{"title":"Preface","order":2,"headings":[{"level":2,"title":"Patterns and Intent","slug":"patterns-and-intent"},{"level":2,"title":"Using the Telegram Archive","slug":"using-the-telegram-archive"},{"level":2,"title":"Changes to this Document","slug":"changes-to-this-document"}]},"/sources/discord-dms":{"title":"Discord DMs","order":99,"headings":[]},"/sources/misc":{"title":"Misc. Sources","headings":[{"level":2,"title":"When I Started Watching Thor’s Stream","slug":"when-i-started-watching-thors-stream"},{"level":2,"title":"Shaye’s Age","slug":"shayes-age"}]},"/sources/recent-events":{"title":"Recent Events","order":0,"headings":[]},"/sources/recollection-of-twitchcon":{"title":"Recollection of TwitchCon","order":7,"headings":[{"level":2,"title":"Filtered Transcript","slug":"filtered-transcript"},{"level":2,"title":"Full Transcript","slug":"full-transcript"}]},"/sources/telegram-archive":{"title":"Telegram Archive","headings":[{"level":2,"title":"Log of first publication","slug":"log-of-first-publication"},{"level":2,"title":"Disclosure of archive modification","slug":"disclosure-of-archive-modification"}]},"/sources/thors-discord":{"title":"Thor's Discord","order":5,"headings":[{"level":2,"title":"Community feedback (2019)","slug":"community-feedback-2019"},{"level":2,"title":"Channel deletion (2022)","slug":"channel-deletion-2022"}]},"/sources/thors-marriage":{"title":"Thor's Marriage","headings":[{"level":2,"title":"Public Records for Marriage and Divorce","slug":"public-records-for-marriage-and-divorce"}]},"/sources/twitter-thread":{"title":"Twitter Thread","order":99,"headings":[]},"/summary":{"title":"Summary","order":-1,"headings":[{"level":2,"title":"How I Met Thor","slug":"how-i-met-thor"},{"level":2,"title":"Constructing Commitment","slug":"constructing-commitment"},{"level":2,"title":"TwitchCon Meetup","slug":"twitchcon-meetup"},{"level":2,"title":"Public Fallout","slug":"public-fallout"},{"level":2,"title":"My Silencing","slug":"my-silencing"},{"level":2,"title":"Effects On My Life","slug":"effects-on-my-life"},{"level":2,"title":"Recent Events","slug":"recent-events"}]},"/twitchcon-2018/final-conversation":{"title":"Final Conversation","order":99,"wip":true,"headings":[{"level":2,"title":"Confronting Thor about Wife","slug":"confronting-thor-about-wife"},{"level":2,"title":"After I spoke with Shaye","slug":"after-i-spoke-with-shaye"},{"level":3,"title":"Annotated transcript","slug":"annotated-transcript"}]},"/twitchcon-2018/meetup":{"title":"Meetup","headings":[{"level":2,"title":"The First Day","slug":"the-first-day"},{"level":2,"title":"The Second Day","slug":"the-second-day"}]}}}